sptygenre/__init__.py
sptygenre/__main__.py
sptygenre/exceptions.py
sptygenre/auth/__init__.py
sptygenre/auth/auth.py
sptygenre/fetch/__init__.py
sptygenre/fetch/fetch.py
sptygenre/ui/__init__.py
sptygenre/ui/draw.py
sptygenre/ui/write.py
sptygenre-1.0.0.dist-info/LICENSE
sptygenre-1.0.0.dist-info/METADATA
sptygenre-1.0.0.dist-info/WHEEL
sptygenre-1.0.0.dist-info/entry_points.txt
sptygenre-1.0.0.dist-info/top_level.txt
sptygenre-1.0.0.dist-info/RECORD
