Metadata-Version: 2.1
Name: sptygenre
Version: 1.0.0
Summary: Draws wordclouds for genres in spotify playlists
Home-page: https://github.com/sublinus/sptygenre
Author: Gabriel Sailer
Author-email: sublinus@riseup.net
License: MIT
Platform: UNKNOWN
Classifier: Development Status :: 4 - Beta
Classifier: Intended Audience :: End Users/Desktop
Classifier: License :: OSI Approved :: MIT License
Classifier: Operating System :: MacOS :: MacOS X
Classifier: Operating System :: POSIX :: Linux
Classifier: Programming Language :: Python :: 2
Classifier: Programming Language :: Python :: 3
Classifier: Programming Language :: Python :: 3.6
Classifier: Topic :: Multimedia :: Sound/Audio :: Analysis
Classifier: Topic :: Scientific/Engineering :: Information Analysis
Requires-Python: >= 2.7
Requires-Dist: matplotlib (>=2.1.1)
Requires-Dist: setuptools
Requires-Dist: spotipy (>=2.4.4)
Requires-Dist: wordcloud (>=1.3.1)
